jinja2_inflection/__init__.py
jinja2_inflection/.skylos/cache.sqlite
jinja2_inflection-0.6.3.dist-info/METADATA
jinja2_inflection-0.6.3.dist-info/WHEEL
jinja2_inflection-0.6.3.dist-info/licenses/LICENSE
jinja2_inflection-0.6.3.dist-info/RECORD
