Metadata-Version: 2.4
Name: jinja2-inflection
Version: 0.6.3
Summary: A Jinja2 extension that integrates the inflection library's string transformation functions as template filters
Project-URL: Homepage, https://github.com/lesleslie/jinja2-inflection
Project-URL: Issues, https://github.com/lesleslie/jinja2-inflection/issues
Author-email: lesleslie <les@wedgwoodwebworks.com>
License: BSD-3-Clause
License-File: LICENSE
Classifier: Development Status :: 4 - Beta
Classifier: License :: OSI Approved :: BSD License
Classifier: Operating System :: OS Independent
Classifier: Programming Language :: Python
Classifier: Programming Language :: Python :: 3.13
Classifier: Topic :: Internet :: WWW/HTTP :: Dynamic Content
Classifier: Topic :: Software Development :: Libraries :: Python Modules
Classifier: Topic :: Text Processing :: Filters
Classifier: Typing :: Typed
Requires-Python: >=3.13
Requires-Dist: inflection>=0.5.1
Requires-Dist: jinja2>=3.1.6
